tensorneko/__init__.py
tensorneko/neko_model.py
tensorneko/neko_module.py
tensorneko/neko_trainer.py
tensorneko/version.txt
tensorneko/arch/__init__.py
tensorneko/arch/auto_encoder.py
tensorneko/arch/binary_classifier.py
tensorneko/arch/gan.py
tensorneko/arch/vqvae.py
tensorneko/arch/wgan.py
tensorneko/backend/__init__.py
tensorneko/callback/__init__.py
tensorneko/callback/display_metrics_callback.py
tensorneko/callback/earlystop_lr.py
tensorneko/callback/epoch_num_logger.py
tensorneko/callback/epoch_time_logger.py
tensorneko/callback/gpu_stats_logger.py
tensorneko/callback/lr_logger.py
tensorneko/callback/nil_callback.py
tensorneko/callback/system_stats_logger.py
tensorneko/dataset/__init__.py
tensorneko/dataset/list_dataset.py
tensorneko/dataset/nested_dataset.py
tensorneko/dataset/round_robin_dataset.py
tensorneko/dataset/sampler/__init__.py
tensorneko/dataset/sampler/sequential_iter_sampler.py
tensorneko/debug/__init__.py
tensorneko/evaluation/__init__.py
tensorneko/evaluation/enum.py
tensorneko/evaluation/fid.py
tensorneko/evaluation/iou.py
tensorneko/evaluation/psnr.py
tensorneko/evaluation/psnr.pyi
tensorneko/evaluation/secs.py
tensorneko/evaluation/ssim.py
tensorneko/evaluation/ssim.pyi
tensorneko/io/__init__.py
tensorneko/io/reader.py
tensorneko/io/writer.py
tensorneko/io/mesh/__init__.py
tensorneko/io/mesh/mesh_reader.py
tensorneko/io/mesh/mesh_writer.py
tensorneko/io/weight/__init__.py
tensorneko/io/weight/weight_reader.py
tensorneko/io/weight/weight_writer.py
tensorneko/layer/__init__.py
tensorneko/layer/aggregation.py
tensorneko/layer/attention.py
tensorneko/layer/concatenate.py
tensorneko/layer/conv.py
tensorneko/layer/linear.py
tensorneko/layer/log.py
tensorneko/layer/masked_conv2d.py
tensorneko/layer/noise.py
tensorneko/layer/patching.py
tensorneko/layer/positional_embedding.py
tensorneko/layer/reshape.py
tensorneko/layer/stack.py
tensorneko/layer/vector_quantizer.py
tensorneko/module/__init__.py
tensorneko/module/dense.py
tensorneko-0.3.22.dist-info/licenses/LICENSE
tensorneko-0.3.22.dist-info/METADATA
tensorneko-0.3.22.dist-info/WHEEL
tensorneko-0.3.22.dist-info/top_level.txt
tensorneko-0.3.22.dist-info/RECORD
