Metadata-Version: 2.4
Name: tensorneko
Version: 0.3.22
Summary: Tensor Neural Engine Kompanion. An util library based on PyTorch and PyTorch Lightning.
Home-page: https://github.com/ControlNet/tensorneko
Author: ControlNet
Author-email: smczx@hotmail.com
Project-URL: Bug Tracker, https://github.com/ControlNet/tensorneko/issues
Project-URL: Source Code, https://github.com/ControlNet/tensorneko
Keywords: deep learning,pytorch,AI,data processing
Classifier: Programming Language :: Python :: 3
Classifier: Programming Language :: Python :: 3.8
Classifier: Programming Language :: Python :: 3.9
Classifier: Programming Language :: Python :: 3.10
Classifier: Programming Language :: Python :: 3.11
Classifier: Programming Language :: Python :: 3.12
Classifier: Programming Language :: Python :: 3.13
Classifier: License :: OSI Approved :: MIT License
Classifier: Operating System :: OS Independent
Classifier: Intended Audience :: Developers
Classifier: Topic :: Scientific/Engineering :: Artificial Intelligence
Classifier: Topic :: Utilities
Requires-Python: >=3.8
License-File: LICENSE
Requires-Dist: torch>=1.9.0
Requires-Dist: torchaudio>=0.9.0
Requires-Dist: torchvision>=0.10.0
Requires-Dist: torchmetrics>=0.7.3
Requires-Dist: pillow>=8.1
Requires-Dist: av>=8.0.3
Requires-Dist: pysoundfile>=0.9.0; platform_system == "Windows"
Requires-Dist: numpy>=1.20.1
Requires-Dist: einops>=0.3.0
Requires-Dist: tensorneko_util==0.3.22
Provides-Extra: lightning
Requires-Dist: tensorboard>=2.0.0; extra == "lightning"
Requires-Dist: lightning<3,>=2.0; extra == "lightning"
Dynamic: author
Dynamic: author-email
Dynamic: classifier
Dynamic: description
Dynamic: description-content-type
Dynamic: home-page
Dynamic: keywords
Dynamic: license-file
Dynamic: project-url
Dynamic: provides-extra
Dynamic: requires-dist
Dynamic: requires-python
Dynamic: summary
